{"label": 0, "event": null, "tstamp": 1.0, "dist": 0.0, "_child0": {"label": 1, "event": "S", "tstamp": 0.8070554120189247, "dist": 0.19294458798107528, "_child0": {"label": 4, "event": "S", "tstamp": 0.0, "dist": 0.8070554120189247}, "_child1": {"label": 5, "event": "S", "tstamp": 0.40968279909399236, "dist": 0.39737261292493237, "_child0": {"label": 6, "event": "S", "tstamp": 0.3401311549250624, "dist": 0.06955164416892995, "_child0": {"label": 9, "event": "S", "tstamp": 0.3390822158764362, "dist": 0.0010489390486261851, "_child0": {"label": 10, "event": "S", "tstamp": 0.2618131144603587, "dist": 0.07726910141607751, "_child0": {"label": 12, "event": "S", "tstamp": 0.0, "dist": 0.2618131144603587}, "_child1": {"label": 13, "event": "S", "tstamp": 0.0, "dist": 0.2618131144603587}}, "_child1": {"label": 11, "event": "S", "tstamp": 0.06508500641580914, "dist": 0.2739972094606271, "_child0": {"label": 14, "event": "S", "tstamp": 0.0, "dist": 0.06508500641580914}, "_child1": {"label": 15, "event": "S", "tstamp": 0.0, "dist": 0.06508500641580914}}}, "_child1": {"label": 8, "event": "S", "tstamp": 0.0, "dist": 0.3401311549250624}}, "_child1": {"label": 7, "event": "S", "tstamp": 0.0, "dist": 0.40968279909399236}}, "_child2": {"label": 2, "event": "S", "tstamp": 0.0, "dist": 0.8070554120189247}}}