{"label": 1, "event": "S", "reconc": 1, "tstamp": 0.6494354171798824, "transferred": 0, "dist": 0.0, "_child0": {"label": 2, "event": "S", "reconc": 2, "tstamp": 0.5929643725811206, "transferred": 0, "dist": 0.06657775188319108, "_child0": {"label": 4, "event": "D", "reconc": [2, 4], "tstamp": 0.15311313089003373, "transferred": 0, "dist": 0.7180995441814275, "_child0": {"label": 15, "event": "S", "reconc": 4, "tstamp": 0.0, "transferred": 0, "dist": 0.3489099334419131}, "_child1": {"label": 16, "event": "S", "reconc": 4, "tstamp": 0.0, "transferred": 0, "dist": 0.24997194296326236}}, "_child1": {"label": 5, "event": "S", "reconc": 5, "tstamp": 0.0, "transferred": 0, "dist": 0.7224408953606535}}, "_child1": {"label": 6, "event": "S", "reconc": 3, "tstamp": 0.45065138371857355, "transferred": 0, "dist": 0.2193448003000255, "_child0": {"label": 10, "event": "H", "reconc": [3, 6], "tstamp": 0.2782683359595069, "transferred": 0, "dist": 0.18092998719504955, "_child0": {"label": 12, "event": "H", "reconc": [2, 5], "tstamp": 0.2094576589656174, "transferred": 1, "dist": 0.08647368744165432, "_child0": {"label": 13, "event": "S", "reconc": 5, "tstamp": 0.0, "transferred": 0, "dist": 0.26322333865806685}, "_child1": {"label": 14, "event": "S", "reconc": 6, "tstamp": 0.0, "transferred": 1, "dist": 0.4692664294263154}}, "_child1": {"label": 11, "event": "H", "reconc": [3, 6], "tstamp": 0.08837011535709245, "transferred": 0, "dist": 0.19931358140261465, "_child0": {"label": 17, "event": "H", "reconc": [3, 6], "tstamp": 0.026684792466141298, "transferred": 0, "dist": 0.06474374844782427, "_child0": {"label": 20, "event": "S", "reconc": 4, "tstamp": 0.0, "transferred": 1, "dist": 0.11986780247213372}, "_child1": {"label": 19, "event": "S", "reconc": 6, "tstamp": 0.0, "transferred": 0, "dist": 0.028007853567768016}}, "_child1": {"label": 18, "event": "S", "reconc": 5, "tstamp": 0.0, "transferred": 1, "dist": 0.10994790644527046}}}, "_child1": {"label": 8, "event": "S", "reconc": 9, "tstamp": 0.0, "transferred": 0, "dist": 0.40140150952435916}, "_child2": {"label": 9, "event": "S", "reconc": 8, "tstamp": 0.0, "transferred": 0, "dist": 0.4645476834881846}}}