{"label": 0, "event": null, "tstamp": 1.0, "dist": 0.0, "_child0": {"label": 1, "event": "S", "tstamp": 0.8953846813803459, "dist": 0.10461531861965412, "_child0": {"label": 8, "event": "S", "tstamp": 0.055747751401235064, "dist": 0.8396369299791108, "_child0": {"label": 13, "event": "S", "tstamp": 0.011672305971293168, "dist": 0.04407544542994189, "_child0": {"label": 14, "event": "S", "tstamp": 0.0, "dist": 0.011672305971293168}, "_child1": {"label": 15, "event": "S", "tstamp": 0.0, "dist": 0.011672305971293168}}, "_child1": {"label": 12, "event": "S", "tstamp": 0.0, "dist": 0.055747751401235064}}, "_child1": {"label": 9, "event": "S", "tstamp": 0.1480013955705462, "dist": 0.7473832858097997, "_child0": {"label": 10, "event": "S", "tstamp": 0.0, "dist": 0.1480013955705462}, "_child1": {"label": 11, "event": "S", "tstamp": 0.0, "dist": 0.1480013955705462}}, "_child2": {"label": 5, "event": "S", "tstamp": 0.4168551255031813, "dist": 0.47852955587716456, "_child0": {"label": 6, "event": "S", "tstamp": 0.0, "dist": 0.4168551255031813}, "_child1": {"label": 7, "event": "S", "tstamp": 0.0, "dist": 0.4168551255031813}}, "_child3": {"label": 2, "event": "S", "tstamp": 0.0, "dist": 0.8953846813803459}}}