{"label": 0, "event": null, "tstamp": 1.0, "dist": 0.0, "_child0": {"label": 1, "event": "S", "tstamp": 0.7661187112691212, "dist": 0.23388128873087877, "_child0": {"label": 4, "event": "S", "tstamp": 0.0, "dist": 0.7661187112691212}, "_child1": {"label": 5, "event": "S", "tstamp": 0.63669501496977, "dist": 0.12942369629935124, "_child0": {"label": 6, "event": "S", "tstamp": 0.5516245949441695, "dist": 0.0850704200256005, "_child0": {"label": 8, "event": "S", "tstamp": 0.0, "dist": 0.5516245949441695}, "_child1": {"label": 9, "event": "S", "tstamp": 0.0, "dist": 0.5516245949441695}}, "_child1": {"label": 7, "event": "S", "tstamp": 0.0, "dist": 0.63669501496977}}, "_child2": {"label": 2, "event": "S", "tstamp": 0.0, "dist": 0.7661187112691212}}}