{"label": 2, "event": "D", "reconc": [1, 3], "tstamp": 0.4165980008354132, "transferred": 0, "dist": 0.0, "_child0": {"label": 4, "event": "S", "reconc": 3, "tstamp": 0.3011705704632826, "transferred": 0, "dist": 0.11123688347828424, "_child0": {"label": 6, "event": "S", "reconc": 5, "tstamp": 0.2671577903683418, "transferred": 0, "dist": 0.03350243865436661, "_child0": {"label": 10, "event": "H", "reconc": [5, 6], "tstamp": 0.15915375111711066, "transferred": 0, "dist": 0.09786120684077779, "_child0": {"label": 14, "event": "S", "reconc": 6, "tstamp": 0.15830754892079416, "transferred": 0, "dist": 0.000766733991959531, "_child0": {"label": 18, "event": "S", "reconc": 8, "tstamp": 0.0, "transferred": 0, "dist": 0.1320246131295581}, "_child1": {"label": 19, "event": "S", "reconc": 9, "tstamp": 0.0, "transferred": 0, "dist": 0.12954419461664587}}, "_child1": {"label": 15, "event": "S", "reconc": 2, "tstamp": 0.0, "transferred": 1, "dist": 0.19290428988221955}}, "_child1": {"label": 11, "event": "D", "reconc": [5, 7], "tstamp": 0.14159581828204754, "transferred": 0, "dist": 0.11739071468765139, "_child0": {"label": 20, "event": "S", "reconc": 7, "tstamp": 0.0, "transferred": 0, "dist": 0.215832083509799}, "_child1": {"label": 21, "event": "S", "reconc": 7, "tstamp": 0.0, "transferred": 0, "dist": 0.13238111849253723}}}, "_child1": {"label": 7, "event": "S", "reconc": 4, "tstamp": 0.0, "transferred": 0, "dist": 0.290492820936999}}, "_child1": {"label": 5, "event": "S", "reconc": 3, "tstamp": 0.3011705704632826, "transferred": 0, "dist": 0.1564590421281596, "_child0": {"label": 8, "event": "S", "reconc": 5, "tstamp": 0.2671577903683418, "transferred": 0, "dist": 0.0353277249072849, "_child0": {"label": 12, "event": "S", "reconc": 6, "tstamp": 0.15830754892079416, "transferred": 0, "dist": 0.09900580296581801, "_child0": {"label": 16, "event": "S", "reconc": 8, "tstamp": 0.0, "transferred": 0, "dist": 0.37621523095982207}, "_child1": {"label": 17, "event": "S", "reconc": 9, "tstamp": 0.0, "transferred": 0, "dist": 0.1298292237947435}}, "_child1": {"label": 13, "event": "S", "reconc": 7, "tstamp": 0.0, "transferred": 0, "dist": 0.2762078120720955}}, "_child1": {"label": 9, "event": "S", "reconc": 4, "tstamp": 0.0, "transferred": 0, "dist": 0.617357352886307}}}