{"label": 0, "event": null, "tstamp": 1.0, "dist": 0.0, "_child0": {"label": 1, "event": "S", "tstamp": 0.48744717342847366, "dist": 0.5125528265715263, "_child0": {"label": 2, "event": "S", "tstamp": 0.25480053844032685, "dist": 0.2326466349881468, "_child0": {"label": 5, "event": "S", "tstamp": 0.20098427663896912, "dist": 0.053816261801357734, "_child0": {"label": 7, "event": "S", "tstamp": 0.024399075121725775, "dist": 0.17658520151724333, "_child0": {"label": 8, "event": "S", "tstamp": 0.0, "dist": 0.024399075121725775}, "_child1": {"label": 9, "event": "S", "tstamp": 0.0, "dist": 0.024399075121725775}}, "_child1": {"label": 6, "event": "S", "tstamp": 0.0, "dist": 0.20098427663896912}}, "_child1": {"label": 4, "event": "S", "tstamp": 0.0, "dist": 0.25480053844032685}}, "_child1": {"label": 3, "event": "S", "tstamp": 0.0, "dist": 0.48744717342847366}}}