{"label": 0, "event": null, "tstamp": 1.0, "dist": 0.0, "_child0": {"label": 1, "event": "S", "tstamp": 0.6885360142166475, "dist": 0.31146398578335255, "_child0": {"label": 3, "event": "S", "tstamp": 0.49099449037312926, "dist": 0.1975415238435182, "_child0": {"label": 5, "event": "S", "tstamp": 0.38274710900187014, "dist": 0.10824738137125911, "_child0": {"label": 7, "event": "S", "tstamp": 0.3803069723114183, "dist": 0.002440136690451844, "_child0": {"label": 9, "event": "S", "tstamp": 0.06534685434157698, "dist": 0.3149601179698413, "_child0": {"label": 10, "event": "S", "tstamp": 0.0, "dist": 0.06534685434157698}, "_child1": {"label": 11, "event": "S", "tstamp": 0.0, "dist": 0.06534685434157698}}, "_child1": {"label": 12, "event": "S", "tstamp": 0.0, "dist": 0.3803069723114183}, "_child2": {"label": 13, "event": "S", "tstamp": 0.0017286711661881507, "dist": 0.37857830114523017, "_child0": {"label": 14, "event": "S", "tstamp": 0.0, "dist": 0.0017286711661881507}, "_child1": {"label": 15, "event": "S", "tstamp": 0.0, "dist": 0.0017286711661881507}}}, "_child1": {"label": 6, "event": "S", "tstamp": 0.0, "dist": 0.38274710900187014}}, "_child1": {"label": 4, "event": "S", "tstamp": 0.0, "dist": 0.49099449037312926}}, "_child1": {"label": 2, "event": "S", "tstamp": 0.0, "dist": 0.6885360142166475}}}