{"label": 0, "event": null, "tstamp": 1.0, "dist": 0.0, "_child0": {"label": 1, "event": "S", "tstamp": 0.9802591579697159, "dist": 0.019740842030284145, "_child0": {"label": 3, "event": "S", "tstamp": 0.950723820001128, "dist": 0.02953533796858787, "_child0": {"label": 5, "event": "S", "tstamp": 0.8722791813490705, "dist": 0.07844463865205753, "_child0": {"label": 8, "event": "S", "tstamp": 0.0, "dist": 0.8722791813490705}, "_child1": {"label": 9, "event": "S", "tstamp": 0.44150617070261033, "dist": 0.4307730106464601, "_child0": {"label": 10, "event": "S", "tstamp": 0.0, "dist": 0.44150617070261033}, "_child1": {"label": 11, "event": "S", "tstamp": 0.0, "dist": 0.44150617070261033}}, "_child2": {"label": 6, "event": "S", "tstamp": 0.0, "dist": 0.8722791813490705}}, "_child1": {"label": 4, "event": "S", "tstamp": 0.0, "dist": 0.950723820001128}}, "_child1": {"label": 12, "event": "S", "tstamp": 0.0, "dist": 0.9802591579697159}, "_child2": {"label": 15, "event": "S", "tstamp": 0.0, "dist": 0.9802591579697159}, "_child3": {"label": 14, "event": "S", "tstamp": 0.0, "dist": 0.9802591579697159}}}