{"label": 0, "event": null, "tstamp": 1.0, "dist": 0.0, "_child0": {"label": 1, "event": "S", "tstamp": 0.9179389920580755, "dist": 0.0820610079419245, "_child0": {"label": 3, "event": "S", "tstamp": 0.8742681354014777, "dist": 0.043670856656597756, "_child0": {"label": 5, "event": "S", "tstamp": 0.5509130137599115, "dist": 0.3233551216415662, "_child0": {"label": 6, "event": "S", "tstamp": 0.5244150532983686, "dist": 0.026497960461542958, "_child0": {"label": 9, "event": "S", "tstamp": 0.37075522347830886, "dist": 0.1536598298200597, "_child0": {"label": 13, "event": "S", "tstamp": 0.0, "dist": 0.37075522347830886}, "_child1": {"label": 12, "event": "S", "tstamp": 0.0, "dist": 0.37075522347830886}, "_child2": {"label": 10, "event": "S", "tstamp": 0.3260763340296024, "dist": 0.04467888944870646, "_child0": {"label": 14, "event": "S", "tstamp": 0.0, "dist": 0.3260763340296024}, "_child1": {"label": 15, "event": "S", "tstamp": 0.0, "dist": 0.3260763340296024}}}, "_child1": {"label": 22, "event": "S", "tstamp": 0.0, "dist": 0.5244150532983686}, "_child2": {"label": 29, "event": "S", "tstamp": 0.0, "dist": 0.5244150532983686}, "_child3": {"label": 28, "event": "S", "tstamp": 0.0, "dist": 0.5244150532983686}, "_child4": {"label": 25, "event": "S", "tstamp": 0.10969898182227565, "dist": 0.4147160714760929, "_child0": {"label": 26, "event": "S", "tstamp": 0.0, "dist": 0.10969898182227565}, "_child1": {"label": 27, "event": "S", "tstamp": 0.0, "dist": 0.10969898182227565}}}, "_child1": {"label": 18, "event": "S", "tstamp": 0.0, "dist": 0.5509130137599115}, "_child2": {"label": 21, "event": "S", "tstamp": 0.0, "dist": 0.5509130137599115}, "_child3": {"label": 20, "event": "S", "tstamp": 0.0, "dist": 0.5509130137599115}}, "_child1": {"label": 4, "event": "S", "tstamp": 0.0, "dist": 0.8742681354014777}}, "_child1": {"label": 2, "event": "S", "tstamp": 0.2360530460947601, "dist": 0.6818859459633154, "_child0": {"label": 16, "event": "S", "tstamp": 0.0, "dist": 0.2360530460947601}, "_child1": {"label": 17, "event": "S", "tstamp": 0.0, "dist": 0.2360530460947601}}}}