{"label": 1, "event": "S", "reconc": 1, "tstamp": 0.7600139439355456, "transferred": 0, "dist": 0.0, "_child0": {"label": 5, "event": "S", "reconc": 2, "tstamp": 0.6388567910824349, "transferred": 1, "dist": 0.17257064841401537, "_child0": {"label": 8, "event": "S", "reconc": 4, "tstamp": 0.47837370314017313, "transferred": 0, "dist": 0.21807031285976966, "_child0": {"label": 12, "event": "S", "reconc": 7, "tstamp": 0.4030326889322556, "transferred": 0, "dist": 0.264750022000051, "_child0": {"label": 16, "event": "S", "reconc": 9, "tstamp": 0.39080234765733, "transferred": 0, "dist": 0.03012992293512252, "_child0": {"label": 20, "event": "S", "reconc": 10, "tstamp": 0.13115727028478477, "transferred": 0, "dist": 0.4426963712993317, "_child0": {"label": 40, "event": "S", "reconc": 21, "tstamp": 0.11185135197787256, "transferred": 0, "dist": 0.034217470504247054, "_child0": {"label": 54, "event": "S", "reconc": 24, "tstamp": 0.0, "transferred": 0, "dist": 0.32266172134733406}, "_child1": {"label": 47, "event": "S", "reconc": 22, "tstamp": 0.07974610919939719, "transferred": 0, "dist": 0.07720455098107716, "_child0": {"label": 63, "event": "S", "reconc": 29, "tstamp": 0.0, "transferred": 0, "dist": 0.14711714656293412}, "_child1": {"label": 59, "event": "S", "reconc": 26, "tstamp": 0.0, "transferred": 0, "dist": 0.10047493754147557}}}, "_child1": {"label": 41, "event": "S", "reconc": 20, "tstamp": 0.0, "transferred": 0, "dist": 0.4340122117904977}}, "_child1": {"label": 21, "event": "H", "reconc": [9, 11], "tstamp": 0.05053925642911816, "transferred": 0, "dist": 0.42073733041577316, "_child0": {"label": 66, "event": "S", "reconc": 11, "tstamp": 0.0, "transferred": 0, "dist": 0.059156161830250784}, "_child1": {"label": 67, "event": "S", "reconc": 18, "tstamp": 0.0, "transferred": 1, "dist": 0.06872961705927007}}}, "_child1": {"label": 17, "event": "H", "reconc": [7, 8], "tstamp": 0.3048015344593372, "transferred": 0, "dist": 0.7385509273603085, "_child0": {"label": 25, "event": "H", "reconc": [9, 11], "tstamp": 0.29497030210332614, "transferred": 1, "dist": 0.04516253623351422, "_child0": {"label": 26, "event": "S", "reconc": 11, "tstamp": 0.0, "transferred": 0, "dist": 1.3550292042896246}, "_child1": {"label": 27, "event": "S", "reconc": 6, "tstamp": 0.0, "transferred": 1, "dist": 0.5943273952541168}}, "_child1": {"label": 24, "event": "S", "reconc": 8, "tstamp": 0.0, "transferred": 0, "dist": 2.2916503134232244}}}, "_child1": {"label": 13, "event": "S", "reconc": 6, "tstamp": 0.0, "transferred": 0, "dist": 1.2403839929025555}}, "_child1": {"label": 9, "event": "S", "reconc": 5, "tstamp": 0.178586672007122, "transferred": 0, "dist": 0.8748798608459898, "_child0": {"label": 32, "event": "S", "reconc": 17, "tstamp": 0.1651713631367682, "transferred": 0, "dist": 0.0184832029160468, "_child0": {"label": 36, "event": "S", "reconc": 18, "tstamp": 0.0, "transferred": 0, "dist": 0.20721004628376682}, "_child1": {"label": 37, "event": "S", "reconc": 19, "tstamp": 0.0, "transferred": 0, "dist": 0.2966738223805324}}, "_child1": {"label": 33, "event": "D", "reconc": [5, 16], "tstamp": 0.0920971325670643, "transferred": 0, "dist": 0.1157162696887882, "_child0": {"label": 53, "event": "H", "reconc": [5, 16], "tstamp": 0.028489764608997124, "transferred": 0, "dist": 0.0829066917338547, "_child0": {"label": 69, "event": "S", "reconc": 28, "tstamp": 0.0, "transferred": 1, "dist": 0.04476131480321563}, "_child1": {"label": 68, "event": "S", "reconc": 16, "tstamp": 0.0, "transferred": 0, "dist": 0.037133939161974744}}, "_child1": {"label": 52, "event": "S", "reconc": 16, "tstamp": 0.0, "transferred": 0, "dist": 0.12004063089582945}}}}, "_child1": {"label": 2, "event": "S", "reconc": 2, "tstamp": 0.6388567910824349, "transferred": 0, "dist": 0.1614926651079705, "_child0": {"label": 6, "event": "S", "reconc": 4, "tstamp": 0.47837370314017313, "transferred": 0, "dist": 0.2126883106182585, "_child0": {"label": 10, "event": "S", "reconc": 7, "tstamp": 0.4030326889322556, "transferred": 0, "dist": 0.08769024836211471, "_child0": {"label": 18, "event": "D", "reconc": [9, 10], "tstamp": 0.30566265513969926, "transferred": 0, "dist": 0.1216961047692672, "_child0": {"label": 22, "event": "H", "reconc": [9, 10], "tstamp": 0.13385786126199128, "transferred": 0, "dist": 0.2156576093967156, "_child0": {"label": 45, "event": "S", "reconc": 20, "tstamp": 0.0, "transferred": 0, "dist": 0.19052064338445807}, "_child1": {"label": 39, "event": "S", "reconc": 6, "tstamp": 0.0, "transferred": 1, "dist": 0.27789359124212554}}, "_child1": {"label": 23, "event": "S", "reconc": 10, "tstamp": 0.13115727028478477, "transferred": 0, "dist": 0.6940839635701144, "_child0": {"label": 42, "event": "S", "reconc": 21, "tstamp": 0.11185135197787256, "transferred": 0, "dist": 0.03992205612161831, "_child0": {"label": 48, "event": "S", "reconc": 23, "tstamp": 0.08860705926368741, "transferred": 0, "dist": 0.1548990390848097, "_child0": {"label": 56, "event": "S", "reconc": 24, "tstamp": 0.0, "transferred": 0, "dist": 0.11243889496360203}, "_child1": {"label": 57, "event": "S", "reconc": 25, "tstamp": 0.0, "transferred": 0, "dist": 0.14914581421807338}}, "_child1": {"label": 49, "event": "S", "reconc": 22, "tstamp": 0.07974610919939719, "transferred": 0, "dist": 0.18190494178663263, "_child0": {"label": 60, "event": "S", "reconc": 27, "tstamp": 0.07538281640013532, "transferred": 0, "dist": 0.010726564117017792, "_child0": {"label": 64, "event": "S", "reconc": 28, "tstamp": 0.0, "transferred": 0, "dist": 0.08276298021110003}, "_child1": {"label": 65, "event": "S", "reconc": 29, "tstamp": 0.0, "transferred": 0, "dist": 0.5293499535718824}}, "_child1": {"label": 61, "event": "S", "reconc": 26, "tstamp": 0.0, "transferred": 0, "dist": 0.7764799814015922}}}, "_child1": {"label": 43, "event": "S", "reconc": 20, "tstamp": 0.0, "transferred": 0, "dist": 0.3838852500705105}}}, "_child1": {"label": 15, "event": "H", "reconc": [7, 8], "tstamp": 0.0017185225070004695, "transferred": 0, "dist": 0.5409342810648711, "_child0": {"label": 70, "event": "S", "reconc": 8, "tstamp": 0.0, "transferred": 0, "dist": 0.002316408974790674}, "_child1": {"label": 71, "event": "S", "reconc": 15, "tstamp": 0.0, "transferred": 1, "dist": 0.00237927291293337}}}, "_child1": {"label": 11, "event": "H", "reconc": [4, 6], "tstamp": 0.2510397974123755, "transferred": 0, "dist": 0.31467866241432463, "_child0": {"label": 28, "event": "H", "reconc": [4, 6], "tstamp": 0.10817387324163384, "transferred": 0, "dist": 0.19775694161725796, "_child0": {"label": 50, "event": "S", "reconc": 6, "tstamp": 0.0, "transferred": 0, "dist": 0.14973573621091285}, "_child1": {"label": 51, "event": "S", "reconc": 18, "tstamp": 0.0, "transferred": 1, "dist": 0.14053724941307275}}, "_child1": {"label": 29, "event": "S", "reconc": 11, "tstamp": 0.0, "transferred": 1, "dist": 0.2962262065752877}}}, "_child1": {"label": 30, "event": "S", "reconc": 17, "tstamp": 0.1651713631367682, "transferred": 0, "dist": 0.6699807530612645, "_child0": {"label": 34, "event": "S", "reconc": 18, "tstamp": 0.0, "transferred": 0, "dist": 0.204145205551466}, "_child1": {"label": 35, "event": "S", "reconc": 19, "tstamp": 0.0, "transferred": 0, "dist": 0.2060508248909566}}}}