{"label": 0, "event": null, "tstamp": 1.0, "dist": 0.0, "_child0": {"label": 1, "event": "S", "tstamp": 0.9930753182004097, "dist": 0.006924681799590271, "_child0": {"label": 2, "event": "S", "tstamp": 0.7287628124024084, "dist": 0.26431250579800136, "_child0": {"label": 5, "event": "S", "tstamp": 0.21357055112804735, "dist": 0.515192261274361, "_child0": {"label": 15, "event": "S", "tstamp": 0.2070819031181949, "dist": 0.006488648009852438, "_child0": {"label": 16, "event": "S", "tstamp": 0.0, "dist": 0.2070819031181949}, "_child1": {"label": 17, "event": "S", "tstamp": 0.0, "dist": 0.2070819031181949}}, "_child1": {"label": 14, "event": "S", "tstamp": 0.0, "dist": 0.21357055112804735}}, "_child1": {"label": 4, "event": "S", "tstamp": 0.0, "dist": 0.7287628124024084}}, "_child1": {"label": 3, "event": "S", "tstamp": 0.6664548838116618, "dist": 0.3266204343887479, "_child0": {"label": 8, "event": "S", "tstamp": 0.0, "dist": 0.6664548838116618}, "_child1": {"label": 9, "event": "S", "tstamp": 0.47010448440377617, "dist": 0.19635039940788568, "_child0": {"label": 11, "event": "S", "tstamp": 0.246791580104201, "dist": 0.22331290429957518, "_child0": {"label": 12, "event": "S", "tstamp": 0.0, "dist": 0.246791580104201}, "_child1": {"label": 13, "event": "S", "tstamp": 0.0, "dist": 0.246791580104201}}, "_child1": {"label": 10, "event": "S", "tstamp": 0.0, "dist": 0.47010448440377617}}, "_child2": {"label": 6, "event": "S", "tstamp": 0.1438656386945063, "dist": 0.5225892451171555, "_child0": {"label": 18, "event": "S", "tstamp": 0.0, "dist": 0.1438656386945063}, "_child1": {"label": 19, "event": "S", "tstamp": 0.0, "dist": 0.1438656386945063}}}}}