{"label": 0, "event": null, "tstamp": 1.0, "dist": 0.0, "_child0": {"label": 1, "event": "S", "tstamp": 0.8051514486927048, "dist": 0.19484855130729517, "_child0": {"label": 4, "event": "S", "tstamp": 0.0, "dist": 0.8051514486927048}, "_child1": {"label": 5, "event": "S", "tstamp": 0.654926772517258, "dist": 0.15022467617544688, "_child0": {"label": 6, "event": "S", "tstamp": 0.0, "dist": 0.654926772517258}, "_child1": {"label": 7, "event": "S", "tstamp": 0.0, "dist": 0.654926772517258}}, "_child2": {"label": 12, "event": "S", "tstamp": 0.0, "dist": 0.8051514486927048}, "_child3": {"label": 13, "event": "S", "tstamp": 0.3814950915920448, "dist": 0.42365635710066, "_child0": {"label": 14, "event": "S", "tstamp": 0.0, "dist": 0.3814950915920448}, "_child1": {"label": 15, "event": "S", "tstamp": 0.0, "dist": 0.3814950915920448}}, "_child4": {"label": 8, "event": "S", "tstamp": 0.5391864688848933, "dist": 0.26596497980781153, "_child0": {"label": 16, "event": "S", "tstamp": 0.0, "dist": 0.5391864688848933}, "_child1": {"label": 19, "event": "S", "tstamp": 0.0, "dist": 0.5391864688848933}, "_child2": {"label": 18, "event": "S", "tstamp": 0.0, "dist": 0.5391864688848933}, "_child3": {"label": 10, "event": "S", "tstamp": 0.0, "dist": 0.5391864688848933}}}}