{"label": 1, "event": "S", "reconc": 1, "tstamp": 0.6205406260225756, "transferred": 0, "dist": 0.0, "_child0": {"label": 2, "event": "H", "reconc": [1, 5], "tstamp": 0.6154009979205529, "transferred": 0, "dist": 0.003748802662626721, "_child0": {"label": 7, "event": "H", "reconc": [1, 5], "tstamp": 0.40309291965675953, "transferred": 0, "dist": 0.15485577424935462, "_child0": {"label": 11, "event": "D", "reconc": [1, 5], "tstamp": 0.3114103833335363, "transferred": 0, "dist": 0.06687249144536453, "_child0": {"label": 13, "event": "S", "reconc": 5, "tstamp": 0.0, "transferred": 0, "dist": 0.2271401842773265}, "_child1": {"label": 14, "event": "S", "reconc": 5, "tstamp": 0.0, "transferred": 0, "dist": 0.2271401842773265}}, "_child1": {"label": 12, "event": "S", "reconc": 8, "tstamp": 0.0, "transferred": 1, "dist": 0.2816914759534812}}, "_child1": {"label": 8, "event": "S", "reconc": 8, "tstamp": 0.0, "transferred": 1, "dist": 0.6782867645741211}}, "_child1": {"label": 3, "event": "H", "reconc": [1, 6], "tstamp": 0.5506903654658014, "transferred": 0, "dist": 0.04429915741538187, "_child0": {"label": 10, "event": "H", "reconc": [1, 3], "tstamp": 0.021049974495786272, "transferred": 1, "dist": 0.9204337151378161, "_child0": {"label": 18, "event": "S", "reconc": 5, "tstamp": 0.0, "transferred": 1, "dist": 0.017279473721017145}, "_child1": {"label": 17, "event": "S", "reconc": 3, "tstamp": 0.0, "transferred": 0, "dist": 0.03658162511591706}}, "_child1": {"label": 9, "event": "S", "reconc": 6, "tstamp": 0.0, "transferred": 0, "dist": 0.349248792952968}}, "_child2": {"label": 5, "event": "H", "reconc": [1, 8], "tstamp": 0.16776765155214335, "transferred": 0, "dist": 0.2862000181548624, "_child0": {"label": 16, "event": "S", "reconc": 6, "tstamp": 0.0, "transferred": 1, "dist": 0.14268098025349152}, "_child1": {"label": 15, "event": "S", "reconc": 8, "tstamp": 0.0, "transferred": 0, "dist": 0.10604675549856082}}, "_child3": {"label": 6, "event": "S", "reconc": 3, "tstamp": 0.0, "transferred": 0, "dist": 0.5766290422698221}}