{"label": 1, "event": "S", "reconc": 1, "tstamp": 0.6246989347292432, "transferred": 0, "dist": 0.0, "_child0": {"label": 2, "event": "S", "reconc": 2, "tstamp": 0.4646687113108099, "transferred": 0, "dist": 0.13076455417823815, "_child0": {"label": 4, "event": "S", "reconc": 4, "tstamp": 0.11131377494880959, "transferred": 0, "dist": 0.2771717552641737, "_child0": {"label": 10, "event": "S", "reconc": 6, "tstamp": 0.0, "transferred": 0, "dist": 0.08108770304652971}, "_child1": {"label": 11, "event": "S", "reconc": 7, "tstamp": 0.0, "transferred": 0, "dist": 0.07410415700784058}}, "_child1": {"label": 5, "event": "S", "reconc": 5, "tstamp": 0.08668848974499795, "transferred": 0, "dist": 0.28634534347023244, "_child0": {"label": 14, "event": "S", "reconc": 8, "tstamp": 0.0, "transferred": 0, "dist": 0.05429161354132906}, "_child1": {"label": 15, "event": "S", "reconc": 9, "tstamp": 0.0, "transferred": 0, "dist": 0.0606718824483813}}}, "_child1": {"label": 3, "event": "H", "reconc": [1, 3], "tstamp": 0.3838908946662449, "transferred": 0, "dist": 0.13778395924970768, "_child0": {"label": 6, "event": "H", "reconc": [1, 3], "tstamp": 0.26892577527991457, "transferred": 0, "dist": 0.06577998525514299, "_child0": {"label": 9, "event": "S", "reconc": 4, "tstamp": 0.11131377494880959, "transferred": 1, "dist": 0.12965592410926882, "_child0": {"label": 13, "event": "D", "reconc": [4, 7], "tstamp": 0.01699062091422887, "transferred": 0, "dist": 0.6981464700558617, "_child0": {"label": 18, "event": "S", "reconc": 7, "tstamp": 0.0, "transferred": 0, "dist": 0.01238983091100749}, "_child1": {"label": 19, "event": "S", "reconc": 7, "tstamp": 0.0, "transferred": 0, "dist": 0.022751576658546813}}, "_child1": {"label": 12, "event": "S", "reconc": 6, "tstamp": 0.0, "transferred": 0, "dist": 0.08154709492639244}}, "_child1": {"label": 8, "event": "S", "reconc": 3, "tstamp": 0.0, "transferred": 0, "dist": 0.15387217990175953}}, "_child1": {"label": 7, "event": "S", "reconc": 5, "tstamp": 0.08668848974499795, "transferred": 1, "dist": 0.7813020823808268, "_child0": {"label": 16, "event": "S", "reconc": 8, "tstamp": 0.0, "transferred": 0, "dist": 0.058788078855377776}, "_child1": {"label": 17, "event": "S", "reconc": 9, "tstamp": 0.0, "transferred": 0, "dist": 0.0872719906460796}}}}