{"label": 0, "event": null, "tstamp": 1.0, "dist": 0.0, "_child0": {"label": 1, "event": "S", "tstamp": 0.7727129870995999, "dist": 0.2272870129004001, "_child0": {"label": 2, "event": "S", "tstamp": 0.7053465534731159, "dist": 0.06736643362648398, "_child0": {"label": 5, "event": "S", "tstamp": 0.6478503655600955, "dist": 0.05749618791302047, "_child0": {"label": 7, "event": "S", "tstamp": 0.6350315407381668, "dist": 0.012818824821928643, "_child0": {"label": 8, "event": "S", "tstamp": 0.0, "dist": 0.6350315407381668}, "_child1": {"label": 9, "event": "S", "tstamp": 0.0, "dist": 0.6350315407381668}}, "_child1": {"label": 6, "event": "S", "tstamp": 0.0, "dist": 0.6478503655600955}}, "_child1": {"label": 4, "event": "S", "tstamp": 0.5955304280924223, "dist": 0.10981612538069363, "_child0": {"label": 12, "event": "S", "tstamp": 0.0, "dist": 0.5955304280924223}, "_child1": {"label": 13, "event": "S", "tstamp": 0.18699286139252616, "dist": 0.40853756669989616, "_child0": {"label": 15, "event": "S", "tstamp": 0.13458781683727708, "dist": 0.05240504455524908, "_child0": {"label": 17, "event": "S", "tstamp": 0.02395055385265216, "dist": 0.11063726298462492, "_child0": {"label": 18, "event": "S", "tstamp": 0.0, "dist": 0.02395055385265216}, "_child1": {"label": 19, "event": "S", "tstamp": 0.0, "dist": 0.02395055385265216}}, "_child1": {"label": 16, "event": "S", "tstamp": 0.0, "dist": 0.13458781683727708}}, "_child1": {"label": 14, "event": "S", "tstamp": 0.0, "dist": 0.18699286139252616}}, "_child2": {"label": 10, "event": "S", "tstamp": 0.0, "dist": 0.5955304280924223}}}, "_child1": {"label": 3, "event": "S", "tstamp": 0.0, "dist": 0.7727129870995999}}}